synax/__init__.py
synax/_attention.py
synax/_basic.py
synax/_compound.py
synax/_misc.py
synax/_parameterizations.py
synax/_recurrent.py
synax/_regularizers.py
synax/_utils.py
synax-0.0.0.dist-info/licenses/LICENSE
synax-0.0.0.dist-info/METADATA
synax-0.0.0.dist-info/WHEEL
synax-0.0.0.dist-info/top_level.txt
synax-0.0.0.dist-info/RECORD
