Metadata-Version: 2.4
Name: synax
Version: 0.0.0
Summary: A neural network library for JAX
Author-email: Carlos Martin <cgmartin@cs.cmu.edu>
License-Expression: MIT
Project-URL: Homepage, https://github.com/carlosgmartin/synax
License-File: LICENSE
Requires-Dist: jax
Provides-Extra: dev
Requires-Dist: ruff; extra == "dev"
Requires-Dist: pyright; extra == "dev"
Requires-Dist: pytest; extra == "dev"
Requires-Dist: furo; extra == "dev"
Requires-Dist: sphinx-autoapi; extra == "dev"
Dynamic: license-file
